compute_api_client/__init__.py
compute_api_client/api/__init__.py
compute_api_client/api/health_controller/__init__.py
compute_api_client/api/health_controller/health_controller_ping.py
compute_api_client/api/job_controller/__init__.py
compute_api_client/api/job_controller/job_controller_create.py
compute_api_client/api/job_controller/job_controller_find.py
compute_api_client/api/job_controller/job_controller_find_by_id.py
compute_api_client/api/job_controller/job_controller_update_by_id.py
compute_api_client/api/pipeline_controller/__init__.py
compute_api_client/api/pipeline_controller/pipeline_controller_create.py
compute_api_client/api/pipeline_controller/pipeline_controller_delete_by_id.py
compute_api_client/api/pipeline_controller/pipeline_controller_find.py
compute_api_client/api/pipeline_controller/pipeline_controller_find_by_id.py
compute_api_client/api/pipeline_controller/pipeline_controller_update_by_id.py
compute_api_client/api/plugin_controller/__init__.py
compute_api_client/api/plugin_controller/plugin_controller_create.py
compute_api_client/api/plugin_controller/plugin_controller_delete_by_id.py
compute_api_client/api/plugin_controller/plugin_controller_find.py
compute_api_client/api/plugin_controller/plugin_controller_find_by_id.py
compute_api_client/api/workflow_controller/__init__.py
compute_api_client/api/workflow_controller/workflow_controller_create.py
compute_api_client/api/workflow_controller/workflow_controller_find.py
compute_api_client/api/workflow_controller/workflow_controller_find_by_id.py
compute_api_client/api/workflow_controller/workflow_controller_get_workflow_jobs.py
compute_api_client/api/workflow_controller/workflow_controller_get_workflow_logs.py
compute_api_client/api/workflow_controller/workflow_controller_get_workflow_output.py
compute_api_client/api/workflow_controller/workflow_controller_get_workflow_status.py
compute_api_client/api/workflow_controller/workflow_controller_health_driver.py
compute_api_client-0.0.3.dist-info/METADATA
compute_api_client-0.0.3.dist-info/WHEEL
compute_api_client-0.0.3.dist-info/RECORD
